Fkillera/__init__.py
Fkillera/operations.py
Fkillera-1.0.0.dist-info/LICENSE.txt
Fkillera-1.0.0.dist-info/METADATA
Fkillera-1.0.0.dist-info/WHEEL
Fkillera-1.0.0.dist-info/entry_points.txt
Fkillera-1.0.0.dist-info/top_level.txt
Fkillera-1.0.0.dist-info/RECORD
